nz/Client.py
nz/__init__.py
nz/utils/__init__.py
nz/utils/exceptions.py
nz/utils/headers.py
nz/utils/helpers.py
nz/utils/objects.py
nz_ua.python-1.1.6.dist-info/METADATA
nz_ua.python-1.1.6.dist-info/WHEEL
nz_ua.python-1.1.6.dist-info/top_level.txt
nz_ua.python-1.1.6.dist-info/RECORD
