Metadata-Version: 2.1
Name: nz-ua.python
Version: 1.1.6
Summary: Library for working with the nz-ua application.
Home-page: https://github.com/xXxCLOTIxXx/nz-ua.py
Download-URL: https://github.com/xXxCLOTIxXx/nz-ua.py/archive/refs/heads/main.zip
Author: Xsarz
Author-email: xsarzy@gmail.com
License: MIT
Keywords: nz,nz_uanz.py,nz-ua,nz-ua.py,nz.ua,asyncapi,python,python3,python3.x,xsarz,official
Requires-Dist: aiohttp
